<?xml version="1.0" encoding="utf-8"?>
<Defs>

  <SoundDef>
    <defName>Pawn_Leopard_Angry</defName>
    <context>MapOnly</context>
    <subSounds>
      <li>
        <grains>
          <li Class="AudioGrain_Folder">
            <clipFolderPath>Pawn/Animal/Leopard/Leopard_Angry</clipFolderPath>
          </li>
        </grains>
        <volumeRange>25.5~26.5</volumeRange>
        <pitchRange>0.9~1.1</pitchRange>
        <distRange>0~70</distRange>
        <sustainLoop>False</sustainLoop>
      </li>
    </subSounds>
  </SoundDef>

  <SoundDef>
    <defName>Pawn_Leopard_Call</defName>
    <context>MapOnly</context>
    <subSounds>
      <li>
        <grains>
          <li Class="AudioGrain_Folder">
            <clipFolderPath>Pawn/Animal/Leopard/Leopard_Call</clipFolderPath>
          </li>
        </grains>
        <volumeRange>25.5~26.5</volumeRange>
        <pitchRange>0.9~1.1</pitchRange>
        <distRange>0~50</distRange>
        <sustainLoop>False</sustainLoop>
      </li>
    </subSounds>
  </SoundDef>

  <SoundDef>
    <defName>Pawn_Leopard_Death</defName>
    <context>MapOnly</context>
    <subSounds>
      <li>
        <grains>
          <li Class="AudioGrain_Folder">
            <clipFolderPath>Pawn/Animal/Leopard/Leopard_Death</clipFolderPath>
          </li>
        </grains>
        <volumeRange>25.5~26.5</volumeRange>
        <pitchRange>0.9~1.1</pitchRange>
        <distRange>0~70</distRange>
        <sustainLoop>False</sustainLoop>
      </li>
    </subSounds>
  </SoundDef>

  <SoundDef>
    <defName>Pawn_Leopard_Wounded</defName>
    <context>MapOnly</context>
    <subSounds>
      <li>
        <grains>
          <li Class="AudioGrain_Folder">
            <clipFolderPath>Pawn/Animal/Leopard/Leopard_Wounded</clipFolderPath>
          </li>
        </grains>
        <volumeRange>25.5~26.5</volumeRange>
        <pitchRange>0.9~1.1</pitchRange>
        <distRange>0~70</distRange>
        <sustainLoop>False</sustainLoop>
      </li>
    </subSounds>
  </SoundDef>

</Defs>